odoo/addons/base_location_city/LICENSE
odoo/addons/base_location_city/README.rst
odoo/addons/base_location_city/__init__.py
odoo/addons/base_location_city/__manifest__.py
odoo/addons/base_location_city/i18n/de_CH.po
odoo/addons/base_location_city/images/screen.png
odoo/addons/base_location_city/models/__init__.py
odoo/addons/base_location_city/models/res_city.py
odoo/addons/base_location_city/models/res_city_zip.py
odoo/addons/base_location_city/static/description/icon.png
odoo/addons/base_location_city/static/description/index.html
odoo/addons/base_location_city/tests/TEST_INSTRUCTIONS.rst
odoo/addons/base_location_city/views/res_city.xml
odoo_addon_base_location_city-18.0.1.0.0.dist-info/METADATA
odoo_addon_base_location_city-18.0.1.0.0.dist-info/WHEEL
odoo_addon_base_location_city-18.0.1.0.0.dist-info/top_level.txt
odoo_addon_base_location_city-18.0.1.0.0.dist-info/RECORD
